transmute_core/__init__.py
transmute_core/_version.py
transmute_core/compat.py
transmute_core/context.py
transmute_core/decorators.py
transmute_core/exceptions.py
transmute_core/handler.py
transmute_core/param_extractor.py
transmute_core/response_shape.py
transmute_core/attributes/__init__.py
transmute_core/attributes/response_type.py
transmute_core/contenttype_serializers/__init__.py
transmute_core/contenttype_serializers/interface.py
transmute_core/contenttype_serializers/json_serializer.py
transmute_core/contenttype_serializers/serializer_set.py
transmute_core/contenttype_serializers/yaml_serializer.py
transmute_core/frameworks/__init__.py
transmute_core/frameworks/aiohttp/__init__.py
transmute_core/frameworks/aiohttp/handler.py
transmute_core/frameworks/aiohttp/route.py
transmute_core/frameworks/aiohttp/swagger.py
transmute_core/frameworks/aiohttp/url_dispatcher.py
transmute_core/frameworks/flask/__init__.py
transmute_core/frameworks/flask/handler.py
transmute_core/frameworks/flask/route.py
transmute_core/frameworks/flask/swagger.py
transmute_core/frameworks/tornado/__init__.py
transmute_core/frameworks/tornado/handler.py
transmute_core/frameworks/tornado/route_set.py
transmute_core/frameworks/tornado/swagger.py
transmute_core/frameworks/tornado/url.py
transmute_core/function/__init__.py
transmute_core/function/parameters.py
transmute_core/function/response.py
transmute_core/function/signature.py
transmute_core/function/transmute_function.py
transmute_core/http_parameters/__init__.py
transmute_core/http_parameters/param_set.py
transmute_core/http_parameters/swagger.py
transmute_core/object_serializers/__init__.py
transmute_core/object_serializers/compound_serializer.py
transmute_core/object_serializers/interface.py
transmute_core/object_serializers/primitive_serializer.py
transmute_core/object_serializers/schematics_serializer.py
transmute_core/object_serializers/serializer_set.py
transmute_core/object_serializers/cattrs_serializer/__init__.py
transmute_core-1.13.7.dist-info/LICENSE
transmute_core-1.13.7.dist-info/METADATA
transmute_core-1.13.7.dist-info/WHEEL
transmute_core-1.13.7.dist-info/top_level.txt
transmute_core-1.13.7.dist-info/zip-safe
transmute_core-1.13.7.dist-info/RECORD
